{
    "id": "2019_11",
    "name": "",
    "memoryVerse": "\"Y a ustedes, ¿quién les va a hacer daño si se esfuerzan por hacer el bien? ¡Dichosos si sufren por causa de la justicia! «No teman lo que ellos temen, ni se dejen asustar»\". – 1 Pedro 3:13-14",
    "dayQuestions": {
        "one": {
            "title": "PRIMER DÍA: lea las notas y las referencias.",
            "questions": [
                {
                    "id": "2019_11_1",
                    "questionText": "1. Anote cómo ha visto la actividad de Dios durante la semana. (¿Cómo ha provisto, contestado, consolado, reconciliado, guiado, etc.?)",
                    "quotes": []
                },
                {
                    "id": "2019_11_2",
                    "questionText": "2. ¿Qué fue lo que más le impactó de las notas, las conferencias, al compartir en grupo o el estudio personal en la semana pasada?",
                    "quotes": []
                }
            ]
        },
        "two": {
            "title": "SEGUNDO DÍA: lea Hechos 13:1-14a.\nEl Espíritu Santo envió a Bernabé y a Saulo.",
            "readVerse": [
                {
                    "book": "Hechos",
                    "verse": "13:1-14"
                }
            ],
            "questions": [
                {
                    "id": "2019_11_3a",
                    "questionText": "3. a. Describa los eventos que llevaron a Pablo y Bernabé ante el gobernador o procónsul.",
                    "quotes": []
                },
                {
                    "id": "2019_11_3b",
                    "questionText": "3. b. Compare y contraste la respuesta a la Palabra de Elimas y el procónsul.",
                    "quotes": []
                },
                {
                    "id": "2019_11_4a",
                    "questionText": "4. a. ¿Qué aprende de la experiencia de Pablo y Bernabé?",
                    "quotes": []
                },
                {
                    "id": "2019_11_4b",
                    "questionText": "4. b. ¿Para qué pudiera Dios estarle apartando? ¿Qué le inspira o desafía sobre esto?",
                    "quotes": []
                }
            ]
        },
        "three": {
            "title": "TERCER DÍA: lea Hechos 13:14b-41.\nPablo continuó el trabajo en Antioquía de Pisidia.",
            "readVerse": [
                {
                    "book": "Hechos",
                    "verse": "13:14-41"
                }
            ],
            "questions": [
                {
                    "id": "2019_11_5",
                    "questionText": "5. El sermón de Pablo tiene tres secciones. Los puntos y versículos clave en la primera parte del sermón (13:16-25) revelan: § ¿La elección de Dios de Israel y Su bondad para con ellos? § ¿El Mesías prometido?",
                    "quotes": []
                },
                {
                    "id": "2019_11_6",
                    "questionText": "6. ¿Qué se revela sobre Jesús y Su obra a nuestro favor en la segunda parte del sermón (13:26-37)?",
                    "quotes": []
                },
                {
                    "id": "2019_11_7",
                    "questionText": "7. ¿Cuál es la advertencia y promesa que se aplica a todos en la tercera parte del sermón (13:38-41)? ¿Cuál es su respuesta?",
                    "quotes": []
                }
            ]
        },
        "four": {
            "title": "CUARTO DÍA: lea Hechos 13:42-52.\nPablo y Bernabé enfrentaron la persecución en su regreso a la sinagoga.",
            "readVerse": [
                {
                    "book": "Hechos",
                    "verse": "13:42-52"
                }
            ],
            "questions": [
                {
                    "id": "2019_11_8",
                    "questionText": "8. ¿Cuál fue la causa de la hostilidad hacia Pablo y Bernabé? ¿Cómo respondieron?",
                    "quotes": []
                },
                {
                    "id": "2019_11_9",
                    "questionText": "9. Pablo y Bernabé experimentaron desgracia y alegrías en Antioquía de Pisidia. ¿Qué le enseña esto acerca de Dios y de servirle?",
                    "quotes": []
                },
                {
                    "id": "2019_11_10",
                    "questionText": "10. ¿Qué obstáculos actuales enfrenta en su trabajo para el Señor? ¿Cómo está respondiendo?",
                    "quotes": []
                }
            ]
        },
        "five": {
            "title": "QUINTO DÍA: lea Hechos 14.\nPablo y Bernabé siguieron siendo testigos a pesar de la severa persecución.",
            "readVerse": [
                {
                    "book": "Hechos",
                    "verse": "14:1-28"
                }
            ],
            "questions": [
                {
                    "id": "2019_11_11",
                    "questionText": "11. De este pasaje, ¿qué sucede cuando la Palabra de Dios se predica eficazmente?",
                    "quotes": []
                },
                {
                    "id": "2019_11_12",
                    "questionText": "12. ¿Qué es lo más preocupante de la respuesta del pueblo en Listra? ¿Cómo son tentadas las personas a adorar al mensajero hoy?",
                    "quotes": []
                },
                {
                    "id": "2019_11_13",
                    "questionText": "13. ¿Qué bendiciones ha visto al compartir y vivir el Evangelio? ¿Qué consecuencias ha experimentado?",
                    "quotes": []
                }
            ]
        },
        "six": {
            "title": "SEXTO DÍA: repase Hechos 13 14.",
            "readVerse": [
                {
                    "book": "Hechos",
                    "verse": "13:1-52"
                },
                {
                    "book": "Hechos",
                    "verse": "14:1-28"
                }
            ],
            "questions": [
                {
                    "id": "2019_11_14",
                    "questionText": "14. ¿Cuál fue su mayor conclusión de su estudio personal de la lección de esta semana?",
                    "quotes": []
                },
                {
                    "id": "2019_11_15",
                    "questionText": "15. Descubrir el pasaje (homilética, estudio de palabras, etc.) para líderes de grupo y administrativos: Hechos 13 14 .",
                    "quotes": [
                        {
                            "book": "Hechos",
                            "verse": "13:1-52"
                        },
                        {
                            "book": "Hechos",
                            "verse": "14:1-28"
                        }
                    ]
                }
            ]
        }
    }
}