{
  "id": "2019_2",
  "name": "",
  "memoryVerse": "“‘不要离开耶路撒冷，要等候父所应许的，就是你们听见我説过的。’”（使徒行传1:4下）",
  "dayQuestions": {
    "one": {
      "title": "第一天：阅读经文释义及参考经文",
      "questions": [
        {
          "id": "2019_2_1",
          "questionText": "1. 试于此处记下本周你怎样看到上帝行事。（如祂怎样供应所需、回应祷吿、安慰心灵、使人和好，或带领指引等等。）",
          "quotes": []
        },
        {
          "id": "2019_2_2",
          "questionText": "2. 在过去一周，经文释义、讲课、小组分享或个人研习的哪些内容对你影响至深？",
          "quotes": []
        }
      ]
    },
    "two": {
      "title": "第二天：阅读使徒行传2:1-13\n圣灵在五旬节降临，并进入使徒心里。",
      "readVerse": [
        {
          "book": "使徒行传",
          "verse": "2:1-13"
        }
      ],
      "questions": [
        {
          "id": "2019_2_3",
          "questionText": "3. 门徒经历了什么外在的景象及声音，让他们认识到一个全新的事实？那内在的、看不见的实况又是什么呢？",
          "quotes": []
        },
        {
          "id": "2019_2_4",
          "questionText": "4. 请分享你自己怎样经历圣灵带来合一。",
          "quotes": []
        },
        {
          "id": "2019_2_5",
          "questionText": "5. 在这场合里，为什么需要有各种不同而又清楚听懂的语言呢？",
          "quotes": []
        }
      ]
    },
    "three": {
      "title": "第三天：阅读使徒行传2:14-21\n彼得对群众讲话，提醒他们关于圣灵降临的应许。",
      "readVerse": [
        {
          "book": "使徒行传",
          "verse": "2:14-21"
        }
      ],
      "questions": [
        {
          "id": "2019_2_6",
          "questionText": "6. 根据彼得所说，这天为什么意义重大？",
          "quotes": []
        },
        {
          "id": "2019_2_7",
          "questionText": "7. 谁领受圣灵？",
          "quotes": []
        },
        {
          "id": "2019_2_8",
          "questionText": "8. 如果圣灵住在你里面，这段经文如何鼓励并催促你去传达上帝的真理及邀请？",
          "quotes": []
        }
      ]
    },
    "four": {
      "title": "第四天：阅读使徒行传2:22-35\n彼得叙述耶稣的受死和复活。",
      "readVerse": [
        {
          "book": "使徒行传",
          "verse": "2:22-35"
        }
      ],
      "questions": [
        {
          "id": "2019_2_9",
          "questionText": "9. 彼得怎样描述上帝、预言和众人在耶稣的受死和复活中的角色？",
          "quotes": []
        },
        {
          "id": "2019_2_10",
          "questionText": "10. 经文中彼得提到了先祖大卫，这有什么重要性？",
          "quotes": []
        },
        {
          "id": "2019_2_11",
          "questionText": "11. 今天的经文，让你发现了哪些上帝（圣父、圣子和圣灵）的属性（或特质）？请在圣经里标示出或于此处写下。你怎样总结你对上帝的认识？",
          "quotes": []
        }
      ]
    },
    "five": {
      "title": "第五天：阅读使徒行传2:36-47\n藉着彼得的教导，许多人相信耶稣基督并接受祂为救主和他们生命的主。",
      "readVerse": [
        {
          "book": "使徒行传",
          "verse": "2:36-47"
        }
      ],
      "questions": [
        {
          "id": "2019_2_12",
          "questionText": "12. 彼得吿诉众人必须做什么来回应他在36节里使他们「扎心」的宣吿？你在什么时候、如何回应了这个宣吿？",
          "quotes": []
        },
        {
          "id": "2019_2_13a",
          "questionText": "13. a. 那些信徒做了什么事情显明了基督徒是怎样生活的？关于教会的合一，这说明了什么？",
          "quotes": []
        },
        {
          "id": "2019_2_13b",
          "questionText": "13. b. 这样的生活在今天的教会里是怎样的？这样的生活在你的生命里是怎样的？",
          "quotes": []
        }
      ]
    },
    "six": {
      "title": "第六天：复习使徒行传第二章",
      "questions": [
        {
          "id": "2019_2_14",
          "questionText": "14. 藉着本周的课程，上帝正如何激励你与世界互动？（组长及班务同工的经文分析练习：本周暂停）",
          "quotes": []
        }
      ]
    }
  }
}
